{
  "title": "The Whispers of Invention",
  "chapters": [
    {
      "title": "The Peculiar Workshop",
      "content": "In the heart of Everwood sat a peculiar workshop. Its owner, Hugo Henley, was a genius inventor with a knack for clockwork wonders and a mysterious air.",
      "image": "https://oaidalleapiprodscus.blob.core.windows.net/private/org-BAl3YpV7pumlbIxLB1lll9Li/user-3GYzta5SGwlZuZnghyMvx5Cc/img-YLxPFIS5u0lxO2KuRxqaXv4v.png?st=2024-09-06T10%3A46%3A06Z&se=2024-09-06T12%3A46%3A06Z&sp=r&sv=2024-08-04&sr=b&rscd=inline&rsct=image/png&skoid=d505667d-d6c1-4a0a-bac7-5c84a87759f8&sktid=a48cca56-e6da-484e-a814-9c849652bcb3&skt=2024-09-05T22%3A03%3A11Z&ske=2024-09-06T22%3A03%3A11Z&sks=b&skv=2024-08-04&sig=EC8XYD9vrLpPTclrRU/fyprISqGRezgOAN10fc0E9Lo%3D"
    },
    {
      "title": "Whispers of the Past",
      "content": "Hugo's inventions amazed all, but whispers circulated about his origins. Some said he once spoke of time travel, hinting at a secret he guarded fiercely.",
      "image": "https://oaidalleapiprodscus.blob.core.windows.net/private/org-BAl3YpV7pumlbIxLB1lll9Li/user-3GYzta5SGwlZuZnghyMvx5Cc/img-IFkvDKUMpaApFaYuPAqUur9R.png?st=2024-09-06T10%3A46%3A06Z&se=2024-09-06T12%3A46%3A06Z&sp=r&sv=2024-08-04&sr=b&rscd=inline&rsct=image/png&skoid=d505667d-d6c1-4a0a-bac7-5c84a87759f8&sktid=a48cca56-e6da-484e-a814-9c849652bcb3&skt=2024-09-05T21%3A40%3A27Z&ske=2024-09-06T21%3A40%3A27Z&sks=b&skv=2024-08-04&sig=gpd2ZJ5MdxaIWXb%2BjnbAcSf2RYbZLpCBTqyr3vfJbH4%3D"
    },
    {
      "title": "The Unveiling",
      "content": "One stormy night, Hugo's latest creation revealed a portal within time itself. Through it, glimpses of Hugo's hidden past emerged, tying together the enigma of his life.",
      "image": "https://oaidalleapiprodscus.blob.core.windows.net/private/org-BAl3YpV7pumlbIxLB1lll9Li/user-3GYzta5SGwlZuZnghyMvx5Cc/img-rVQAwqbyCg4eaeLxvSutZNgp.png?st=2024-09-06T10%3A46%3A04Z&se=2024-09-06T12%3A46%3A04Z&sp=r&sv=2024-08-04&sr=b&rscd=inline&rsct=image/png&skoid=d505667d-d6c1-4a0a-bac7-5c84a87759f8&sktid=a48cca56-e6da-484e-a814-9c849652bcb3&skt=2024-09-05T21%3A20%3A58Z&ske=2024-09-06T21%3A20%3A58Z&sks=b&skv=2024-08-04&sig=6et3Bivqu/Vm%2BTtODSk39snlr05FXHD8hSPDRdsWBgw%3D"
    }
  ]
}
